odoo8_addon_event_sale_extra_info-8.0.1.0.0-py2.7-nspkg.pth
odoo8_addon_event_sale_extra_info-8.0.1.0.0.dist-info/top_level.txt
odoo8_addon_event_sale_extra_info-8.0.1.0.0.dist-info/WHEEL
odoo8_addon_event_sale_extra_info-8.0.1.0.0.dist-info/RECORD
odoo8_addon_event_sale_extra_info-8.0.1.0.0.dist-info/metadata.json
odoo8_addon_event_sale_extra_info-8.0.1.0.0.dist-info/DESCRIPTION.rst
odoo8_addon_event_sale_extra_info-8.0.1.0.0.dist-info/METADATA
odoo8_addon_event_sale_extra_info-8.0.1.0.0.dist-info/namespace_packages.txt
odoo_addons/event_sale_extra_info/__openerp__.py
odoo_addons/event_sale_extra_info/__init__.py
odoo_addons/event_sale_extra_info/README.rst
odoo_addons/event_sale_extra_info/report/__init__.py
odoo_addons/event_sale_extra_info/report/report_event_registration.py
odoo_addons/event_sale_extra_info/models/__init__.py
odoo_addons/event_sale_extra_info/models/event.py
odoo_addons/event_sale_extra_info/i18n/es.po
odoo_addons/event_sale_extra_info/views/event_registration_view.xml
odoo_addons/event_sale_extra_info/images/bi-report-view.png
odoo_addons/event_sale_extra_info/images/search-view.png
odoo_addons/event_sale_extra_info/images/form-view.png
odoo_addons/event_sale_extra_info/static/description/icon.png
